[
    {
        "header": "Sinharaja Rain forest",
        "images": [
            {
                "src": "./Introduction to wildlife/sinharaja1.jpg",
                "reference": "https://www.rainforest-ecolodge.com/sinharaja-rainforest.html"
            },
            {
                "src": "./Introduction to wildlife/sinharaja2.jpg",
                "reference": "https://www.lovidhu.com/travel/article/sinharaja-forest-reserve"
            },
            {
                "src": "./Introduction to wildlife/sinharaja3.jpg",
                "reference": "https://www.klook.com/activity/9247-sinharaja-rainforest-day-trek-colombo/"
            },
            {
                "src": "./Introduction to wildlife/sinharaja4.jpg",
                "reference": "https://imgs.mongabay.com/wp-content/uploads/sites/20/2019/12/17004731/canopy-by-Vimukthi-W-768x512.jpg"
            }
        ],
        "paragraph": "Sinharaja Forest Reserve, located in the southwestern part of Sri Lanka, stands as one of the last remaining undisturbed tropical rainforests globally and has earned UNESCO World Heritage status. The name \"Sinharaja,\" meaning \"Lion King,\" underscores its significance and biodiversity. This lush sanctuary is a haven for numerous endemic species, both flora, and fauna, making it a biodiversity hotspot. The forest houses a myriad of plant species, including rare and unique ones found exclusively in Sri Lanka. With its ecological importance, strict conservation measures, and limited access to core areas, Sinharaja serves not only as a captivating destination for nature enthusiasts but also as a crucial reservoir for scientific research, environmental education, and sustainable eco-tourism initiatives.",
        "map": "https://www.google.com/maps/embed?pb=!1m18!1m12!1m3!1d7929.7983131956935!2d80.45049939357914!3d6.406990799999997!2m3!1f0!2f0!3f0!3m2!1i1024!2i768!4f13.1!3m3!1m2!1s0x3ae3e76bd109d45f%3A0x8c0ef1010649701b!2sSinharaja%20Forest%20Reserve!5e0!3m2!1sen!2slk!4v1705558578520!5m2!1sen!2slk"
    },
    {
        "header": "Horton Plains",
        "images": [
            {
                "src": "./Introduction to wildlife/horton1.jpg",
                "reference": "https://www.theweek.in/leisure/travel/2018/02/19/horton-plains-sri-lanka-is-anything-but-plain.html"
            },
            {
                "src": "./Introduction to wildlife/horton2.jpg",
                "reference": "https://www.cinnamonnaturetrails.com/destinations/horton-plains-national-park.html"
            },
            {
                "src": "./Introduction to wildlife/horton3.jpg",
                "reference": "https://www.classicsrilanka.com/blog/2021/04/28/leopard-tracking-in-the-misty-highlands-of-horton-plains/"
            },
            {
                "src": "./Introduction to wildlife/horton4.jpg",
                "reference": "https://www.srilankanexpeditions.com/best-things-to-do-in-horton-plains.php"
            }
        ],
        "paragraph": "Horton Plains National Park, situated in the central highlands of Sri Lanka, is a unique and scenic plateau known for its distinctive landscape and biodiversity. Characterized by grasslands, montane forests, and the striking escarpment known as World's End, the park boasts an array of endemic flora and fauna. Notable features include Baker's Falls and the iconic World's End viewpoint, offering breathtaking panoramic views. Home to species such as the elusive sambar deer, purple-faced langur, and a variety of endemic bird species, Horton Plains is a haven for nature enthusiasts and hikers seeking a captivating highland experience in Sri Lanka.",
        "map": "https://www.google.com/maps/embed?pb=!1m18!1m12!1m3!1d3961.6739945881054!2d80.79975837448211!3d6.809451319775396!2m3!1f0!2f0!3f0!3m2!1i1024!2i768!4f13.1!3m3!1m2!1s0x3ae3882edb4b78ef%3A0xcebca89153777249!2sHorton%20Plains%20National%20Park!5e0!3m2!1sen!2slk!4v1705558645522!5m2!1sen!2slk"
    },
    {
        "header": "Kumana National Park",
        "images": [
            {
                "src": "./Introduction to wildlife/kumana1.jpg",
                "reference": "https://en.wikipedia.org/wiki/Kumana_National_Park"
            },
            {
                "src": "./Introduction to wildlife/kumana2.jpg",
                "reference": "https://www.reddottours.com/sri-lanka-activities/kumana-national-park"
            },
            {
                "src": "./Introduction to wildlife/kumana3.jpg",
                "reference": "https://www.lankatravelguide.com/st_activity/kumana-national-park/"
            },
            {
                "src": "./Introduction to wildlife/kumana4.jpg",
                "reference": "https://www.yovoyagin.com/news/camping-in-kumana-national-wildlife-sanctuary-ampara"
            }
        ],
        "paragraph": "Kumana National Park, located in the southeastern corner of Sri Lanka, is renowned for its diverse ecosystems, encompassing wetlands, mangroves, and coastal plains. Recognized as a vital bird sanctuary, Kumana is a haven for avian enthusiasts, especially during the migratory season from April to July when it hosts a plethora of waterfowl species. The park is home to the scenic Kumana Villu, a large mangrove swamp, providing an ideal breeding ground for various bird species. Beyond its rich birdlife, Kumana also supports a range of wildlife, including elephants, leopards, and crocodiles, making it a captivating destination for nature lovers and wildlife photographers alike.",
        "map": "https://www.google.com/maps/embed?pb=!1m18!1m12!1m3!1d3963.592797150062!2d81.66438227563194!3d6.572965105648362!2m3!1f0!2f0!3f0!3m2!1i1024!2i768!4f13.1!3m3!1m2!1s0x3ae5c8b55f7156a3%3A0xce605bccbb80201a!2sKumana%20National%20Park!5e0!3m2!1sen!2slk!4v1705558701824!5m2!1sen!2slk"
    },
    {
        "header": "Udawalawa National Park",
        "images": [
            {
                "src": "./Introduction to wildlife/udawalawa1.jpg",
                "reference": "https://www.klook.com/en-IN/activity/24794-udawalawe-national-park-private-safari-tour-bentota/"
            },
            {
                "src": "./Introduction to wildlife/udawalawa2.jpg",
                "reference": "https://www.thecommonwanderer.com/blog/udawalawe-national-park-safari-sri-lanka"
            },
            {
                "src": "./Introduction to wildlife/udawalawa3.jpg",
                "reference": "https://overatours.com/trip/udawalawe-national-park-safari/"
            },
            {
                "src": "./Introduction to wildlife/udawalawa4.jpg",
                "reference": "https://mirissatourscabs.com/destination/udawalawe-national-park/"
            }
        ],
        "paragraph": "Udawalawe National Park, nestled in the southern part of Sri Lanka, is a prominent wildlife sanctuary celebrated for its thriving population of elephants. Established to protect the reservoir and its catchment area, Udawalawe has evolved into a key destination for wildlife enthusiasts. The park's picturesque landscapes, characterized by grasslands, scrublands, and the Udawalawe Reservoir, provide an ideal habitat for diverse fauna. In addition to elephants, visitors can encounter water buffaloes, sambar deer, and various bird species. Jeep safaris through the park offer a unique opportunity to witness these animals in their natural habitat, making Udawalawe a popular destination for those seeking an immersive wildlife experience in Sri Lanka.",
        "map": "https://www.google.com/maps/embed?pb=!1m18!1m12!1m3!1d3964.370762013673!2d80.8737440744802!3d6.474634123730347!2m3!1f0!2f0!3f0!3m2!1i1024!2i768!4f13.1!3m3!1m2!1s0x3ae408ff88887e79%3A0xaf12e79ffbd980d7!2sUdawalawe%20National%20Park!5e0!3m2!1sen!2slk!4v1705558738557!5m2!1sen!2slk"
    }
]
